.gitignore
.gitlab-ci.yml
LICENSE
Readme.rst
setup.py
py2venv.egg-info/PKG-INFO
py2venv.egg-info/SOURCES.txt
py2venv.egg-info/dependency_links.txt
py2venv.egg-info/requires.txt
py2venv.egg-info/top_level.txt
venv/__init__.py
venv/__main__.py