Metadata-Version: 1.0
Name: py2venv
Version: 1.1
Summary: Shortcut from virtualenv to venv for python2
Home-page: https://gitlab.com/alelec/py2venv
Author: Andrew Leech
Author-email: andrew@alelec.net
License: MIT
Platform: UNKNOWN
